deployment-service-lamda/__init__.py
old_services_cicd2/__init__.py
old_services_cicd2/classes/Repository.py
old_services_cicd2/classes/Suppliers.py
old_services_cicd2/classes/TypeProjectEnum.py
old_services_cicd2/classes/__init__.py
old_services_cicd2/classes/dataClass.py
old_services_cicd2/interfaces/CICDService.py
old_services_cicd2/interfaces/Repository.py
old_services_cicd2/interfaces/__init__.py
old_services_cicd2/service/__init__.py
old_services_cicd2/service/demo.py
old_services_cicd2/service/src/__init__.py
old_services_cicd2/service/src/Interfaces/__init__.py
old_services_cicd2/service/src/Interfaces/git.py
old_services_cicd2/service/src/Interfaces/interfaces.py
old_services_cicd2/service/src/classes/__init__.py
old_services_cicd2/service/src/classes/dataClass.py
old_services_cicd2/service/src/classes/github.py
old_services_cicd2/service/src/classes/gitlab.py
old_services_cicd2/service/src/classes/jenkins.py
old_services_cicd2/service/src/classes/jenkinsAPI.py
old_services_cicd2/service/src/classes/vercel.py
old_services_cicd2/service/src/classes/vercelAPI.py
old_services_cicd2/service/src/utils/__init__.py
old_services_cicd2/service/src/utils/utils.py
old_services_cicd2/service/test/__init__.py
old_services_cicd2/service/test/test_api_vercel.py
old_services_cicd2/service/test/test_github.py
old_services_cicd2/service/test/test_gitlab.py
old_services_cicd2/service/test/test_jenkins.py
old_services_cicd2/service/test/test_vercel.py
old_services_cicd2/service/test/test_xml_jenkins.py
services_cicd/__init__.py
services_cicd/src/__init__.py
services_cicd/src/classes/Repository.py
services_cicd/src/classes/Suppliers.py
services_cicd/src/classes/TypeProjectEnum.py
services_cicd/src/classes/__init__.py
services_cicd/src/classes/dataClass.py
services_cicd/src/interfaces/CICDService.py
services_cicd/src/interfaces/Repository.py
services_cicd/src/interfaces/__init__.py
services_cicd/src/service/__init__.py
services_cicd/src/service/src/__init__.py
services_cicd-1.0.dist-info/METADATA
services_cicd-1.0.dist-info/WHEEL
services_cicd-1.0.dist-info/top_level.txt
services_cicd-1.0.dist-info/RECORD
