Metadata-Version: 2.1
Name: services-cicd
Version: 1.0
Summary: Testing installation of Package
Home-page: https://github.com/torrencia/test
Author: auth
Author-email: author@email.com
License: MIT
Platform: UNKNOWN
